exprun/__init__.py
exprun/experiment.py
exprun/runner.py
exprun-0.0.1.dist-info/LICENSE
exprun-0.0.1.dist-info/METADATA
exprun-0.0.1.dist-info/WHEEL
exprun-0.0.1.dist-info/top_level.txt
exprun-0.0.1.dist-info/RECORD
