Metadata-Version: 2.1
Name: exprun
Version: 0.0.1
Summary: exprun: Automatized python pipelines to run reproducible experiments.
Author-email: Theo Guyard <guyard.theo@gmail.com>
License: MIT License
Project-URL: Homepage, https://github.com/TheoGuyard/ExpRun
Project-URL: Issues, https://github.com/TheoGuyard/ExpRun/issues
Requires-Python: >=3.9
License-File: LICENSE
Requires-Dist: pyyaml
Provides-Extra: dev
Requires-Dist: black; extra == "dev"
Requires-Dist: build; extra == "dev"
Requires-Dist: flake8; extra == "dev"
Requires-Dist: numpy; extra == "dev"
Requires-Dist: pytest; extra == "dev"
Requires-Dist: twine; extra == "dev"
